rai_gnns_experimental/CHANGELOG.md
rai_gnns_experimental/LICENCE
rai_gnns_experimental/README.md
rai_gnns_experimental/__init__.py
rai_gnns_experimental/_version.py
rai_gnns_experimental/instructions_to_add_sdk_to_sf_notebooks.MD
rai_gnns_experimental/common/__init__.py
rai_gnns_experimental/common/dataset_model.py
rai_gnns_experimental/common/exceptions.py
rai_gnns_experimental/common/export.py
rai_gnns_experimental/common/job_models.py
rai_gnns_experimental/core/__init__.py
rai_gnns_experimental/core/api_request_handler.py
rai_gnns_experimental/core/config_trainer.py
rai_gnns_experimental/core/connector.py
rai_gnns_experimental/core/custom_sqlalchemy_dtypes.py
rai_gnns_experimental/core/dataset.py
rai_gnns_experimental/core/gnn_table.py
rai_gnns_experimental/core/job_manager.py
rai_gnns_experimental/core/metrics.py
rai_gnns_experimental/core/model_manager.py
rai_gnns_experimental/core/provider.py
rai_gnns_experimental/core/task.py
rai_gnns_experimental/core/trainer.py
rai_gnns_experimental/core/types.py
rai_gnns_experimental/core/utils.py
rai_gnns_experimental/external/__init__.py
rai_gnns_experimental/external/db_diagram.py
rai_gnns_experimental/external/model_diagram.py
rai_gnns_experimental-0.1.3.post2.dist-info/METADATA
rai_gnns_experimental-0.1.3.post2.dist-info/WHEEL
rai_gnns_experimental-0.1.3.post2.dist-info/top_level.txt
rai_gnns_experimental-0.1.3.post2.dist-info/RECORD
