Metadata-Version: 2.4
Name: rai_gnns_experimental
Version: 0.1.3.post2
Summary: GNN Relational Learning Engine SDK
License: Apache-2.0
Requires-Python: >=3.10
Requires-Dist: annotated-types==0.7.0
Requires-Dist: asn1crypto==1.5.1
Requires-Dist: black==25.1.0
Requires-Dist: certifi==2025.1.31
Requires-Dist: cffi==1.17.1
Requires-Dist: charset-normalizer==3.4.1
Requires-Dist: click==8.2.1
Requires-Dist: cloudpickle==2.2.1
Requires-Dist: cryptography==43.0.3
Requires-Dist: filelock==3.18.0
Requires-Dist: greenlet==3.1.1
Requires-Dist: graphviz==0.20.3
Requires-Dist: idna==3.10
Requires-Dist: jupyter-black==0.4.0
Requires-Dist: mypy-extensions==1.0.0
Requires-Dist: numpy==1.26.4
Requires-Dist: pandas==2.2.3
Requires-Dist: pathspec==0.12.1
Requires-Dist: pillow==11.1.0
Requires-Dist: protobuf==4.25.8
Requires-Dist: pycparser==2.22
Requires-Dist: pydantic==2.11.0
Requires-Dist: pydot==3.0.4
Requires-Dist: pyjwt==2.10.1
Requires-Dist: pyopenssl==25.0.0
Requires-Dist: pyparsing==3.2.3
Requires-Dist: pytz==2025.2
Requires-Dist: pyyaml==6.0.2
Requires-Dist: requests==2.32.3
Requires-Dist: snowflake-connector-python==4.0.0
Requires-Dist: snowflake-snowpark-python==1.42.0
Requires-Dist: sortedcontainers==2.4.0
Requires-Dist: sqlalchemy==2.0.40
Requires-Dist: tabulate==0.9.0
Requires-Dist: tokenize-rt==6.1.0
Requires-Dist: tomlkit==0.13.2
Requires-Dist: tzdata==2025.2
Requires-Dist: tzlocal==5.3.1
Requires-Dist: urllib3==2.3.0
Requires-Dist: ipykernel==6.29.5
Requires-Dist: build==1.2.2
Requires-Dist: python-dotenv==1.1.0
Requires-Dist: pyarrow==18.1.0
